{
  "coord": {
    "lon": -0.1257,
    "lat": 51.5085
  },
  "weather": [
    {
      "id": 802,
      "main": "Clouds",
      "description": "scattered clouds",
      "icon": "03n"
    }
  ],
  "base": "stations",
  "main": {
    "temp": 25.14,
    "feels_like": 25.2,
    "temp_min": 23.84,
    "temp_max": 26.42,
    "pressure": 1019,
    "humidity": 57,
    "sea_level": 1019,
    "grnd_level": 1014
  },
  "visibility": 10000,
  "wind": {
    "speed": 2.16,
    "deg": 175,
    "gust": 4.36
  },
  "clouds": {
    "all": 29
  },
  "dt": 1783549700,
  "sys": {
    "type": 2,
    "id": 2006068,
    "country": "GB",
    "sunrise": 1783482784,
    "sunset": 1783541858
  },
  "timezone": 3600,
  "id": 2643743,
  "name": "London",
  "cod": 200,
  "last_updated": "2026-07-08T22:30:47Z"
}
